scdlp/__init__.py
scdlp/cli.py
scdlp/prep.py
scdlp-0.1.dist-info/METADATA
scdlp-0.1.dist-info/WHEEL
scdlp-0.1.dist-info/entry_points.txt
scdlp-0.1.dist-info/top_level.txt
scdlp-0.1.dist-info/RECORD
