Metadata-Version: 2.1
Name: scdlp
Version: 0.1
Summary: UNKNOWN
Home-page: https://github.com/jayvishaalj/scdlp
Author: jayvishaalj
Author-email: jayvishaalj.01@gmail.com
License: UNKNOWN
Platform: UNKNOWN
Requires-Dist: click (==7.1.2)
Requires-Dist: GitPython (==2.1.15)
Requires-Dist: pyfiglet (==0.8.post1)
Requires-Dist: PyInquirer (==1.0.3)
Requires-Dist: six (==1.15.0)
Requires-Dist: regex (==2020.11.13)
Requires-Dist: colorama (==0.4.4)
Requires-Dist: termcolor (==1.1.0)
Requires-Dist: halo
